mxnet/__init__.py
mxnet/attribute.py
mxnet/autograd.py
mxnet/base.py
mxnet/callback.py
mxnet/context.py
mxnet/cudnn64_7.dll
mxnet/engine.py
mxnet/executor.py
mxnet/executor_manager.py
mxnet/initializer.py
mxnet/io.py
mxnet/kvstore.py
mxnet/kvstore_server.py
mxnet/libgcc_s_seh-1.dll
mxnet/libgfortran-3.dll
mxnet/libinfo.py
mxnet/libmxnet.dll
mxnet/libmxnet.lib
mxnet/libopenblas.dll
mxnet/libquadmath-0.dll
mxnet/log.py
mxnet/lr_scheduler.py
mxnet/metric.py
mxnet/misc.py
mxnet/model.py
mxnet/monitor.py
mxnet/name.py
mxnet/ndarray_doc.py
mxnet/operator.py
mxnet/optimizer.py
mxnet/profiler.py
mxnet/random.py
mxnet/recordio.py
mxnet/registry.py
mxnet/rtc.py
mxnet/symbol_doc.py
mxnet/test_utils.py
mxnet/torch.py
mxnet/util.py
mxnet/visualization.py
mxnet/_ctypes/__init__.py
mxnet/_ctypes/ndarray.py
mxnet/_ctypes/symbol.py
mxnet/_cy2/__init__.py
mxnet/_cy3/__init__.py
mxnet/contrib/__init__.py
mxnet/contrib/autograd.py
mxnet/contrib/io.py
mxnet/contrib/ndarray.py
mxnet/contrib/quantization.py
mxnet/contrib/symbol.py
mxnet/contrib/tensorboard.py
mxnet/contrib/tensorrt.py
mxnet/contrib/onnx/__init__.py
mxnet/contrib/onnx/mx2onnx/__init__.py
mxnet/contrib/onnx/mx2onnx/_export_helper.py
mxnet/contrib/onnx/mx2onnx/_op_translations.py
mxnet/contrib/onnx/mx2onnx/export_model.py
mxnet/contrib/onnx/mx2onnx/export_onnx.py
mxnet/contrib/onnx/onnx2mx/__init__.py
mxnet/contrib/onnx/onnx2mx/_import_helper.py
mxnet/contrib/onnx/onnx2mx/_op_translations.py
mxnet/contrib/onnx/onnx2mx/_translation_utils.py
mxnet/contrib/onnx/onnx2mx/import_model.py
mxnet/contrib/onnx/onnx2mx/import_onnx.py
mxnet/contrib/onnx/onnx2mx/import_to_gluon.py
mxnet/contrib/text/__init__.py
mxnet/contrib/text/_constants.py
mxnet/contrib/text/embedding.py
mxnet/contrib/text/utils.py
mxnet/contrib/text/vocab.py
mxnet/gluon/__init__.py
mxnet/gluon/block.py
mxnet/gluon/loss.py
mxnet/gluon/parameter.py
mxnet/gluon/trainer.py
mxnet_cu91-1.3.0.dist-info/METADATA
mxnet_cu91-1.3.0.dist-info/RECORD
mxnet_cu91-1.3.0.dist-info/WHEEL
mxnet_cu91-1.3.0.dist-info/top_level.txt
